pipelinevilma/Collector.py
pipelinevilma/CollectorDataApi.py
pipelinevilma/Estimator.py
pipelinevilma/EstimatorActor.py
pipelinevilma/Evaluator.py
pipelinevilma/FileManager.py
pipelinevilma/Filesystem.py
pipelinevilma/Instancer.py
pipelinevilma/Messager.py
pipelinevilma/Provider.py
pipelinevilma/TrainerClassication.py
pipelinevilma/TrainerDetection.py
pipelinevilma/__init__.py
pipelinevilma/packer/AirQuality.py
pipelinevilma/packer/BasePackage.py
pipelinevilma/packer/Environment.py
pipelinevilma/packer/Heatmap.py
pipelinevilma/packer/Image.py
pipelinevilma/packer/ImageBase64.py
pipelinevilma/packer/ImageUrl.py
pipelinevilma/packer/Instance.py
pipelinevilma/packer/MetaType.py
pipelinevilma/packer/Text.py
pipelinevilma/packer/__init__.py
pipeline_vilma-0.0.32.dist-info/LICENSE
pipeline_vilma-0.0.32.dist-info/METADATA
pipeline_vilma-0.0.32.dist-info/WHEEL
pipeline_vilma-0.0.32.dist-info/top_level.txt
pipeline_vilma-0.0.32.dist-info/RECORD
