Metadata-Version: 2.1
Name: pipeline-vilma
Version: 0.0.32
Summary: Data pipeline
Home-page: https://github.com/cjcbusatto/pipeline-vilma
Author: Claudio Busatto
Author-email: cjcbusatto@gmail.com
License: MIT
Platform: UNKNOWN
Classifier: Programming Language :: Python :: 3
Classifier: License :: OSI Approved :: MIT License
Classifier: Operating System :: OS Independent
Requires-Python: >=3.6
Requires-Dist: loguru (==0.3.2)
Requires-Dist: pika (==1.1.0)
Requires-Dist: requests (==2.22.0)
